{
"meta":{"test_sets":[],"test_metrics":[],"learn_metrics":[{"best_value":"Min","name":"RMSE"}],"launch_mode":"Train","parameters":"","iteration_count":100,"learn_sets":["learn"],"name":"experiment"},
"iterations":[
{"learn":[14.005006],"iteration":0,"passed_time":0.001841628407,"remaining_time":0.1823212123},
{"learn":[13.14441192],"iteration":1,"passed_time":0.003329561324,"remaining_time":0.1631485049},
{"learn":[12.34258257],"iteration":2,"passed_time":0.004809205556,"remaining_time":0.1554976463},
{"learn":[11.64527793],"iteration":3,"passed_time":0.005970483311,"remaining_time":0.1432915995},
{"learn":[11.02766183],"iteration":4,"passed_time":0.007466958975,"remaining_time":0.1418722205},
{"learn":[10.43485794],"iteration":5,"passed_time":0.008866683605,"remaining_time":0.1389113765},
{"learn":[9.890641275],"iteration":6,"passed_time":0.01032250318,"remaining_time":0.137141828},
{"learn":[9.492161212],"iteration":7,"passed_time":0.01177462714,"remaining_time":0.1354082121},
{"learn":[9.105082953],"iteration":8,"passed_time":0.01317678661,"remaining_time":0.1332319535},
{"learn":[8.674157135],"iteration":9,"passed_time":0.01471300963,"remaining_time":0.1324170867},
{"learn":[8.341743544],"iteration":10,"passed_time":0.01611880749,"remaining_time":0.130415806},
{"learn":[8.049372916],"iteration":11,"passed_time":0.01756186844,"remaining_time":0.1287870352},
{"learn":[7.757318612],"iteration":12,"passed_time":0.01896778855,"remaining_time":0.1269382772},
{"learn":[7.522206899],"iteration":13,"passed_time":0.02043369173,"remaining_time":0.1255212492},
{"learn":[7.297756655],"iteration":14,"passed_time":0.02188253282,"remaining_time":0.1240010193},
{"learn":[7.088359431],"iteration":15,"passed_time":0.02333875906,"remaining_time":0.1225284851},
{"learn":[6.882113791],"iteration":16,"passed_time":0.02479302912,"remaining_time":0.1210483186},
{"learn":[6.704728832],"iteration":17,"passed_time":0.0261758278,"remaining_time":0.1192454378},
{"learn":[6.563881962],"iteration":18,"passed_time":0.02762423794,"remaining_time":0.1177664881},
{"learn":[6.418790279],"iteration":19,"passed_time":0.02924036366,"remaining_time":0.1169614546},
{"learn":[6.315756953],"iteration":20,"passed_time":0.03069612947,"remaining_time":0.1154759156},
{"learn":[6.210157751],"iteration":21,"passed_time":0.03214744616,"remaining_time":0.1139773091},
{"learn":[6.115058449],"iteration":22,"passed_time":0.03356258276,"remaining_time":0.1123616901},
{"learn":[6.014819884],"iteration":23,"passed_time":0.03504103038,"remaining_time":0.1109632629},
{"learn":[5.93117229],"iteration":24,"passed_time":0.03649637132,"remaining_time":0.1094891139},
{"learn":[5.844857622],"iteration":25,"passed_time":0.03792162274,"remaining_time":0.1079307724},
{"learn":[5.771145213],"iteration":26,"passed_time":0.03937128845,"remaining_time":0.1064482984},
{"learn":[5.704018229],"iteration":27,"passed_time":0.04086423932,"remaining_time":0.1050794725},
{"learn":[5.665806474],"iteration":28,"passed_time":0.04263039725,"remaining_time":0.1043709726},
{"learn":[5.616500369],"iteration":29,"passed_time":0.044144072,"remaining_time":0.1030028347},
{"learn":[5.558023666],"iteration":30,"passed_time":0.04557174612,"remaining_time":0.1014338865},
{"learn":[5.510080976],"iteration":31,"passed_time":0.04700804363,"remaining_time":0.09989209271},
{"learn":[5.468747792],"iteration":32,"passed_time":0.04847312912,"remaining_time":0.09841514094},
{"learn":[5.429275534],"iteration":33,"passed_time":0.04992217831,"remaining_time":0.09690775791},
{"learn":[5.402117324],"iteration":34,"passed_time":0.05136264921,"remaining_time":0.09538777711},
{"learn":[5.367635151],"iteration":35,"passed_time":0.05294355084,"remaining_time":0.09412186816},
{"learn":[5.345181232],"iteration":36,"passed_time":0.05442701382,"remaining_time":0.09267302352},
{"learn":[5.319151269],"iteration":37,"passed_time":0.05586029726,"remaining_time":0.091140485},
{"learn":[5.296134146],"iteration":38,"passed_time":0.05732254557,"remaining_time":0.08965834051},
{"learn":[5.269629003],"iteration":39,"passed_time":0.05877578897,"remaining_time":0.08816368345},
{"learn":[5.251147059],"iteration":40,"passed_time":0.0602095762,"remaining_time":0.08664304867},
{"learn":[5.248003302],"iteration":41,"passed_time":0.06082566418,"remaining_time":0.08399734577},
{"learn":[5.232376509],"iteration":42,"passed_time":0.06225689864,"remaining_time":0.08252658658},
{"learn":[5.213524255],"iteration":43,"passed_time":0.06368926642,"remaining_time":0.08105906635},
{"learn":[5.189691584],"iteration":44,"passed_time":0.06508431994,"remaining_time":0.07954750215},
{"learn":[5.166052198],"iteration":45,"passed_time":0.06660764256,"remaining_time":0.0781915804},
{"learn":[5.140406659],"iteration":46,"passed_time":0.06819434774,"remaining_time":0.07690000916},
{"learn":[5.118929684],"iteration":47,"passed_time":0.06963645921,"remaining_time":0.07543949748},
{"learn":[5.108792602],"iteration":48,"passed_time":0.07109684498,"remaining_time":0.07399875702},
{"learn":[5.098141225],"iteration":49,"passed_time":0.07252915205,"remaining_time":0.07252915205},
{"learn":[5.085926393],"iteration":50,"passed_time":0.07392999438,"remaining_time":0.07103077892},
{"learn":[5.067816804],"iteration":51,"passed_time":0.07533896412,"remaining_time":0.06954365919},
{"learn":[5.049834901],"iteration":52,"passed_time":0.07676019302,"remaining_time":0.06807035985},
{"learn":[5.03838627],"iteration":53,"passed_time":0.07817849891,"remaining_time":0.06659649907},
{"learn":[5.033534248],"iteration":54,"passed_time":0.07915102114,"remaining_time":0.06475992639},
{"learn":[5.023726885],"iteration":55,"passed_time":0.08059132816,"remaining_time":0.06332175784},
{"learn":[5.01290392],"iteration":56,"passed_time":0.08210514511,"remaining_time":0.06193896912},
{"learn":[5.005569127],"iteration":57,"passed_time":0.08356808538,"remaining_time":0.06051482045},
{"learn":[4.989969032],"iteration":58,"passed_time":0.08502932264,"remaining_time":0.05908817336},
{"learn":[4.976762446],"iteration":59,"passed_time":0.08649922058,"remaining_time":0.05766614706},
{"learn":[4.967222715],"iteration":60,"passed_time":0.08797699273,"remaining_time":0.05624758552},
{"learn":[4.954407599],"iteration":61,"passed_time":0.08941884146,"remaining_time":0.05480509638},
{"learn":[4.942125056],"iteration":62,"passed_time":0.09082437051,"remaining_time":0.05334129697},
{"learn":[4.930230716],"iteration":63,"passed_time":0.09229427279,"remaining_time":0.05191552844},
{"learn":[4.921695642],"iteration":64,"passed_time":0.09372742356,"remaining_time":0.05046861269},
{"learn":[4.906405625],"iteration":65,"passed_time":0.09525498374,"remaining_time":0.0490707492},
{"learn":[4.894330248],"iteration":66,"passed_time":0.09679205393,"remaining_time":0.04767369821},
{"learn":[4.88211557],"iteration":67,"passed_time":0.09824330298,"remaining_time":0.04623214258},
{"learn":[4.877946398],"iteration":68,"passed_time":0.0996421579,"remaining_time":0.04476676659},
{"learn":[4.863182126],"iteration":69,"passed_time":0.1010338124,"remaining_time":0.0433002053},
{"learn":[4.84646533],"iteration":70,"passed_time":0.1024665573,"remaining_time":0.0418525375},
{"learn":[4.838014752],"iteration":71,"passed_time":0.1039215072,"remaining_time":0.04041391946},
{"learn":[4.82981137],"iteration":72,"passed_time":0.105390186,"remaining_time":0.0389799318},
{"learn":[4.817094767],"iteration":73,"passed_time":0.1067940008,"remaining_time":0.03752221648},
{"learn":[4.808314151],"iteration":74,"passed_time":0.1082492333,"remaining_time":0.03608307777},
{"learn":[4.796235023],"iteration":75,"passed_time":0.1096326554,"remaining_time":0.03462083856},
{"learn":[4.784434534],"iteration":76,"passed_time":0.1111075748,"remaining_time":0.03318797689},
{"learn":[4.774402487],"iteration":77,"passed_time":0.112526296,"remaining_time":0.03173818606},
{"learn":[4.76731896],"iteration":78,"passed_time":0.1140231229,"remaining_time":0.03030994405},
{"learn":[4.75934113],"iteration":79,"passed_time":0.1154050397,"remaining_time":0.02885125992},
{"learn":[4.754106378],"iteration":80,"passed_time":0.1172156343,"remaining_time":0.02749502533},
{"learn":[4.744002932],"iteration":81,"passed_time":0.1188327732,"remaining_time":0.02608524291},
{"learn":[4.731700554],"iteration":82,"passed_time":0.1202867515,"remaining_time":0.02463704549},
{"learn":[4.723284153],"iteration":83,"passed_time":0.1218451409,"remaining_time":0.02320859826},
{"learn":[4.712232782],"iteration":84,"passed_time":0.1232794978,"remaining_time":0.02175520549},
{"learn":[4.703046867],"iteration":85,"passed_time":0.1246879308,"remaining_time":0.02029803524},
{"learn":[4.698601855],"iteration":86,"passed_time":0.1261742977,"remaining_time":0.01885363069},
{"learn":[4.692429407],"iteration":87,"passed_time":0.1275652593,"remaining_time":0.01739526264},
{"learn":[4.675027364],"iteration":88,"passed_time":0.129005373,"remaining_time":0.0159444843},
{"learn":[4.662368584],"iteration":89,"passed_time":0.1304483065,"remaining_time":0.01449425627},
{"learn":[4.646206172],"iteration":90,"passed_time":0.1319618459,"remaining_time":0.01305117158},
{"learn":[4.641245848],"iteration":91,"passed_time":0.1333664507,"remaining_time":0.01159708267},
{"learn":[4.633900435],"iteration":92,"passed_time":0.1347860208,"remaining_time":0.01014518436},
{"learn":[4.624738236],"iteration":93,"passed_time":0.1362127142,"remaining_time":0.008694428566},
{"learn":[4.612798287],"iteration":94,"passed_time":0.1376432151,"remaining_time":0.007244379742},
{"learn":[4.605222001],"iteration":95,"passed_time":0.1390029721,"remaining_time":0.005791790505},
{"learn":[4.601725912],"iteration":96,"passed_time":0.1403717609,"remaining_time":0.004341394668},
{"learn":[4.59722371],"iteration":97,"passed_time":0.1417614913,"remaining_time":0.002893091659},
{"learn":[4.580235665],"iteration":98,"passed_time":0.1431319215,"remaining_time":0.001445776985},
{"learn":[4.57591791],"iteration":99,"passed_time":0.1448822422,"remaining_time":0}
]}